juham_visualcrossing/__init__.py
juham_visualcrossing/py.typed
juham_visualcrossing/visualcrossing.py
juham_visualcrossing/visualcrossing_plugin.py
juham_visualcrossing-0.1.10.dist-info/licenses/LICENSE.rst
juham_visualcrossing-0.1.10.dist-info/METADATA
juham_visualcrossing-0.1.10.dist-info/WHEEL
juham_visualcrossing-0.1.10.dist-info/entry_points.txt
juham_visualcrossing-0.1.10.dist-info/top_level.txt
juham_visualcrossing-0.1.10.dist-info/RECORD
