Metadata-Version: 2.4
Name: juham-visualcrossing
Version: 0.1.10
Summary: A Weather forecast  plugin extending `Juham` applications
Author-email: J Meskanen <juham.api@gmail.com>
Maintainer-email: "J. Meskanen" <juham.api@gmail.com>
License-Expression: MIT
Project-URL: Homepage, https://gitlab.com/juham/juham/juham-visualcrossing
Project-URL: Bug Reports, https://gitlab.com/juham/juham/juham-visualcrossing
Project-URL: Funding, https://meskanen.com
Project-URL: Say Thanks!, http://meskanen.com
Project-URL: Source, https://gitlab.com/juham/juham/juham-visualcrossing
Keywords: object-oriented,plugin,framework
Classifier: Development Status :: 3 - Alpha
Classifier: Intended Audience :: Developers
Classifier: Topic :: Software Development
Classifier: Programming Language :: Python :: 3.8
Requires-Python: >=3.8
License-File: LICENSE.rst
Requires-Dist: juham-core>=0.2.6
Requires-Dist: pytz>=2024.1
Provides-Extra: dev
Requires-Dist: check-manifest; extra == "dev"
Dynamic: license-file
